jupyterlab_todo/__init__.py
jupyterlab_todo/_version.py
jupyterlab_todo-1.0.0.data/data/share/jupyter/labextensions/jupyterlab_todo/build_log.json
jupyterlab_todo-1.0.0.data/data/share/jupyter/labextensions/jupyterlab_todo/package.json
jupyterlab_todo-1.0.0.data/data/share/jupyter/labextensions/jupyterlab_todo/static/lib_index_js.bd2229b04d6b0e1fd18b.js
jupyterlab_todo-1.0.0.data/data/share/jupyter/labextensions/jupyterlab_todo/static/lib_index_js.bd2229b04d6b0e1fd18b.js.map
jupyterlab_todo-1.0.0.data/data/share/jupyter/labextensions/jupyterlab_todo/static/remoteEntry.1b1eed80f2cfaa82e17a.js
jupyterlab_todo-1.0.0.data/data/share/jupyter/labextensions/jupyterlab_todo/static/remoteEntry.1b1eed80f2cfaa82e17a.js.map
jupyterlab_todo-1.0.0.data/data/share/jupyter/labextensions/jupyterlab_todo/static/style.js
jupyterlab_todo-1.0.0.data/data/share/jupyter/labextensions/jupyterlab_todo/static/style_index_js.0c160c90b9d6db5a579b.js
jupyterlab_todo-1.0.0.data/data/share/jupyter/labextensions/jupyterlab_todo/static/style_index_js.0c160c90b9d6db5a579b.js.map
jupyterlab_todo-1.0.0.data/data/share/jupyter/labextensions/jupyterlab_todo/install.json
jupyterlab_todo-1.0.0.dist-info/METADATA
jupyterlab_todo-1.0.0.dist-info/WHEEL
jupyterlab_todo-1.0.0.dist-info/licenses/LICENSE
jupyterlab_todo-1.0.0.dist-info/RECORD
